ex7_1/lfsr/design/lfsr.sv
// Generalizing the LFSR Module
// The difference between all LFSRs of this type (fibonacci / external LFSRs) is the size of the register (num bits) the tap configuration, and some would say the initial seed.
// Changing the seed doesn't change the sequence, it just changes where you start in the sequence, but we can say that this is another difference.
// Other then that we still just need to create a register shift the bits over and calculate the new bit based on the taps chosen.
// Let's create a file called lfsr.v with a module accepting these as parameters:

`default_nettype none 

module lfsr 
#(
  parameter SEED = 5'd1,
  parameter TAPS = 5'h1B,
  parameter NUM_BITS = 5
)
(
  input  wire clk,
  output reg  randomBit 
);
  reg [NUM_BITS-1:0] sr = SEED; //  create a register of the desired size holding our seed value as it's initial value
  wire finalFeedback; // a wire which will hold the feedback after the feedback calculation (XORs). 
  
  always_ff@(posedge clk) begin   // The calculation each clock cycle:
    sr <= {sr[NUM_BITS-2:0], finalFeedback}; // shifting all the bits up 1 and putting our feedback bit into b0.
    randomBit <= sr[NUM_BITS-1]; // output bit
  end
  
  // How do we XOR the bits from our taps to generate the final feedback bit.
  // We can simply go over all bits and either XOR them or XOR a zero, XOR-ing a zero doesn't affect the output, its like multiplying by one.
  // we will chain each bit with the value of the previous bit's feedback XOR-ed either with it or with a zero if it is not a tap. 
  genvar i;
  generate  //  "generate" repetitive verilog code using loops instead.
    for(i=0; i < NUM_BITS; i = i+1) begin: lf   // So we loop over all the bits storing the current index inside i, we also name this loop lf (linear feedback) so that we will have a reference to access any wires or registers defined inside.
      wire feedback; // In each iteration of the loop we create a feedback wire and we connect it to one of two things. 
      if(i==0) // If we are on the first bit, there is no previous bit, so we simply take the current bit (sr[i]) AND-ed together with the same bit from the TAP parameter.
        assign feedback = sr[i] & TAPS[i]; // What this is doing is either evaluating to the value of current bit sr[i] if the TAP bit is 1, or making these two evaluate to zero if the TAP is not part of the XOR equation. By making it zero it won't affect the XOR operation.
      else
        assign feedback = lf[i-1].feedback ^ (sr[i] & TAPS[i]); // For all the other bits we take the previous feedback and XOR it with the same AND equation to either make it a zero if it is not part of our XOR equation, or return the value of sr[i].
    end
  endgenerate 
  assign finalFeedback = lf[NUM_BITS-1].feedback; // Take the output of the (last) XOR-ing. Connect the feedback from the final iteration to the wire we created finalFeedback: 
  // With that we now have a fully working LFSR of any size and any tap configuration.
endmodule

ex7_1/lfsr/testbench/lfsr_tb.sv
// With that we now have a fully working LFSR of any size and any tap configuration. To test it let's create a test bench so we can simulate a few different LFSRs 
// so in a file called lfsr_tb.v:
module test();
  reg clk = 0;
  wire l1Bit, l2Bit, l3Bit; 

  // we are simply creating 3 LFSRs. They are all 5 bits with an initial seed of 1, but each has a different tap configuration.
  lfsr #(
    .SEED(5'd1),
    .TAPS(5'h12),
    .NUM_BITS(5)
  ) l1 (
    clk,
    l1Bit
  );

  lfsr #(
    .SEED(5'd1),
    .TAPS(5'h1B),
    .NUM_BITS(5)
  ) l2 (
    clk,
    l2Bit
  );

  lfsr #(
    .SEED(5'd1),
    .TAPS(5'h1B),
    .NUM_BITS(5)
  ) l3 (
    clk,
    l3Bit
  );

  // The way to simulate the clock signal.
  always begin 
    #1 clk = ~clk; // The #number (#1) is a special simulation syntax from iverilog that allows us to delay something by a certain number of time frames. 
                  // By saying each time interval the clock alternates, we are saying the clock cycle is 2 time units (1 high cycle and 1 low cycle is 1 clock cycle).
                  // So this loop will wait 1 time unit and toggle the clock register.
  end 
  
  // Start & Stop the simulation
  initial begin 
    $display("Starting LFSR Test"); // print out a string optionally injecting variables into it - performed once
    #1000 $finish; // stops the simulation, so after 1000 more time frames we stop the simulation.
  end

  // For visually debugging the logic we can add another block to dump a VCD file.
  initial begin 
    $dumpfile("lfsr.vcd"); // $dumpfile chooses the name of the file - VCD file 
    $dumpvars(0,test ); // chooses what to save and how many levels of nested objects to save. By sending 0 as the number of layers it means we want all nested layers
                        // (which will include our LFSR test module), and by sending the top module test it means store everything and all child wires / registers.
  end
endmodule

ex7_1/lfsr/simulation/lfsr_tb-waves.vcd
$date 
$end
$version DSim 2025
$end
$timescale 1 ns $end
$scope module $pkgs $end
$scope module std $end
$scope function randomize $end
$upscope $end
$upscope $end
$upscope $end
$scope module $unit $end
$upscope $end
$scope module test $end
$scope module l1 $end
$scope begin lf[0] $end
$scope begin genblk1 $end
$upscope $end
$var wire 1 ( feedback $end
$upscope $end
$scope begin lf[1] $end
$scope begin genblk1 $end
$upscope $end
$var wire 1 ) feedback $end
$upscope $end
$scope begin lf[2] $end
$scope begin genblk1 $end
$upscope $end
$var wire 1 * feedback $end
$upscope $end
$scope begin lf[3] $end
$scope begin genblk1 $end
$upscope $end
$var wire 1 + feedback $end
$upscope $end
$scope begin lf[4] $end
$scope begin genblk1 $end
$upscope $end
$var wire 1 ' feedback $end
$upscope $end
$var wire 1 " clk $end
$var wire 1 ' finalFeedback $end
$var reg 1 # randomBit $end
$var reg 5 & sr[4:0] $end
$upscope $end
$scope module l2 $end
$scope begin lf[0] $end
$scope begin genblk1 $end
$upscope $end
$var wire 1 . feedback $end
$upscope $end
$scope begin lf[1] $end
$scope begin genblk1 $end
$upscope $end
$var wire 1 / feedback $end
$upscope $end
$scope begin lf[2] $end
$scope begin genblk1 $end
$upscope $end
$var wire 1 0 feedback $end
$upscope $end
$scope begin lf[3] $end
$scope begin genblk1 $end
$upscope $end
$var wire 1 1 feedback $end
$upscope $end
$scope begin lf[4] $end
$scope begin genblk1 $end
$upscope $end
$var wire 1 - feedback $end
$upscope $end
$var wire 1 " clk $end
$var wire 1 - finalFeedback $end
$var reg 1 $ randomBit $end
$var reg 5 , sr[4:0] $end
$upscope $end
$scope module l3 $end
$scope begin lf[0] $end
$scope begin genblk1 $end
$upscope $end
$var wire 1 4 feedback $end
$upscope $end
$scope begin lf[1] $end
$scope begin genblk1 $end
$upscope $end
$var wire 1 5 feedback $end
$upscope $end
$scope begin lf[2] $end
$scope begin genblk1 $end
$upscope $end
$var wire 1 6 feedback $end
$upscope $end
$scope begin lf[3] $end
$scope begin genblk1 $end
$upscope $end
$var wire 1 7 feedback $end
$upscope $end
$scope begin lf[4] $end
$scope begin genblk1 $end
$upscope $end
$var wire 1 3 feedback $end
$upscope $end
$var wire 1 " clk $end
$var wire 1 3 finalFeedback $end
$var reg 1 % randomBit $end
$var reg 5 2 sr[4:0] $end
$upscope $end
$var reg 1 " clk $end
$var wire 1 # l1Bit $end
$var wire 1 $ l2Bit $end
$var wire 1 % l3Bit $end
$upscope $end
$enddefinitions $end
#0
$dumpvars
x(
x)
x*
x+
x'
0"
x'
x#
b01 &
x.
x/
x0
x1
x-
0"
x-
x$
b01 ,
x4
x5
x6
x7
x3
0"
x3
x%
b01 2
0"
x#
x$
x%
$end
0(
0)
0*
0+
0'
1.
1/
10
11
1-
14
15
16
17
13
#1
1"
b010 &
0#
b011 ,
0$
b011 2
0%
1)
1*
1+
1'
0/
00
01
0-
05
06
07
03
#2
0"
#3
1"
b0101 &
b0110 ,
b0110 2
0)
0*
0+
0'
0.
1/
10
11
1-
04
15
16
17
13
#4
0"
#5
1"
b01010 &
b01101 ,
b01101 2
1)
1*
1+
1'
1.
01
0-
14
07
03
#6
0"
#7
1"
b10101 &
b11010 ,
b11010 2
0)
0*
0+
0.
1-
04
13
#8
0"
#9
1"
b01011 &
1#
b10101 ,
1$
b10101 2
1%
1)
1*
1+
1.
11
0-
14
17
03
#10
0"
#11
1"
b10111 &
0#
b01010 ,
b01010 2
0'
0.
01
04
07
#12
0"
#13
1"
b01110 &
1#
b10100 ,
0$
b10100 2
0%
1'
0/
00
1-
05
06
13
#14
0"
#15
1"
b11101 &
0#
b01001 ,
1$
b01001 2
1%
0)
0*
0+
1.
1/
10
0-
14
15
16
03
#16
0"
#17
1"
b11011 &
1#
b10010 ,
0$
b10010 2
0%
1)
1*
1+
0'
0.
11
04
17
#18
0"
#19
1"
b10110 &
b0100 ,
1$
b0100 2
1%
0/
00
01
05
06
07
#20
0"
#21
1"
b01100 &
b01000 ,
0$
b01000 2
0%
0)
0*
0+
11
1-
17
13
#22
0"
#23
1"
b11000 &
0#
b10001 ,
b10001 2
1'
1.
1/
10
0-
14
15
16
03
#24
0"
#25
1"
b10001 &
1#
b010 ,
1$
b010 2
1%
0.
1-
04
13
#26
0"
#27
1"
b011 &
b0101 ,
0$
b0101 2
0%
1)
1*
1+
1.
14
#28
0"
#29
1"
b0111 &
0#
b01011 ,
b01011 2
0/
00
05
06
#30
0"
#31
1"
b01111 &
b10111 ,
b10111 2
01
07
#32
0"
#33
1"
b11111 &
b01111 ,
1$
b01111 2
1%
0'
11
17
#34
0"
#35
1"
b11110 &
1#
b11111 ,
0$
b11111 2
0%
0-
03
#36
0"
#37
1"
b11100 &
b11110 ,
1$
b11110 2
1%
0)
0*
0+
1'
0.
1/
10
01
1-
04
15
16
07
13
#38
0"
#39
1"
b11001 &
b11101 ,
b11101 2
1.
14
#40
0"
#41
1"
b10011 &
b11011 ,
b11011 2
1)
1*
1+
0'
0/
00
11
0-
05
06
17
03
#42
0"
#43
1"
b0110 &
b10110 ,
b10110 2
1'
0.
1/
10
04
15
16
#44
0"
#45
1"
b01101 &
0#
b01100 ,
b01100 2
0)
0*
0+
0'
0/
00
1-
05
06
13
#46
0"
#47
1"
b11010 &
b11001 ,
0$
b11001 2
0%
1)
1*
1+
1.
1/
10
01
14
15
16
07
#48
0"
#49
1"
b10100 &
1#
b10011 ,
1$
b10011 2
1%
0)
0*
0+
1'
0/
00
05
06
#50
0"
#51
1"
b01001 &
b0111 ,
b0111 2
0'
0-
03
#52
0"
#53
1"
b10010 &
0#
b01110 ,
0$
b01110 2
0%
1)
1*
1+
0.
1/
10
04
15
16
#54
0"
#55
1"
b0100 &
1#
b11100 ,
b11100 2
0)
0*
0+
0/
00
11
05
06
17
#56
0"
#57
1"
b01000 &
0#
b11000 ,
1$
b11000 2
1%
#58
0"
#59
1"
b10000 &
b10000 ,
b10000 2
1'
01
1-
07
13
#60
0"
#61
1"
b01 &
1#
b01 ,
b01 2
0'
1.
1/
10
11
14
15
16
17
#62
0"
#63
1"
b010 &
0#
b011 ,
0$
b011 2
0%
1)
1*
1+
1'
0/
00
01
0-
05
06
07
03
#64
0"
#65
1"
b0101 &
b0110 ,
b0110 2
0)
0*
0+
0'
0.
1/
10
11
1-
04
15
16
17
13
#66
0"
#67
1"
b01010 &
b01101 ,
b01101 2
1)
1*
1+
1'
1.
01
0-
14
07
03
#68
0"
#69
1"
b10101 &
b11010 ,
b11010 2
0)
0*
0+
0.
1-
04
13
#70
0"
#71
1"
b01011 &
1#
b10101 ,
1$
b10101 2
1%
1)
1*
1+
1.
11
0-
14
17
03
#72
0"
#73
1"
b10111 &
0#
b01010 ,
b01010 2
0'
0.
01
04
07
#74
0"
#75
1"
b01110 &
1#
b10100 ,
0$
b10100 2
0%
1'
0/
00
1-
05
06
13
#76
0"
#77
1"
b11101 &
0#
b01001 ,
1$
b01001 2
1%
0)
0*
0+
1.
1/
10
0-
14
15
16
03
#78
0"
#79
1"
b11011 &
1#
b10010 ,
0$
b10010 2
0%
1)
1*
1+
0'
0.
11
04
17
#80
0"
#81
1"
b10110 &
b0100 ,
1$
b0100 2
1%
0/
00
01
05
06
07
#82
0"
#83
1"
b01100 &
b01000 ,
0$
b01000 2
0%
0)
0*
0+
11
1-
17
13
#84
0"
#85
1"
b11000 &
0#
b10001 ,
b10001 2
1'
1.
1/
10
0-
14
15
16
03
#86
0"
#87
1"
b10001 &
1#
b010 ,
1$
b010 2
1%
0.
1-
04
13
#88
0"
#89
1"
b011 &
b0101 ,
0$
b0101 2
0%
1)
1*
1+
1.
14
#90
0"
#91
1"
b0111 &
0#
b01011 ,
b01011 2
0/
00
05
06
#92
0"
#93
1"
b01111 &
b10111 ,
b10111 2
01
07
#94
0"
#95
1"
b11111 &
b01111 ,
1$
b01111 2
1%
0'
11
17
#96
0"
#97
1"
b11110 &
1#
b11111 ,
0$
b11111 2
0%
0-
03
#98
0"
#99
1"
b11100 &
b11110 ,
1$
b11110 2
1%
0)
0*
0+
1'
0.
1/
10
01
1-
04
15
16
07
13
#100
0"
#101
1"
b11001 &
b11101 ,
b11101 2
1.
14
#102
0"
#103
1"
b10011 &
b11011 ,
b11011 2
1)
1*
1+
0'
0/
00
11
0-
05
06
17
03
#104
0"
#105
1"
b0110 &
b10110 ,
b10110 2
1'
0.
1/
10
04
15
16
#106
0"
#107
1"
b01101 &
0#
b01100 ,
b01100 2
0)
0*
0+
0'
0/
00
1-
05
06
13
#108
0"
#109
1"
b11010 &
b11001 ,
0$
b11001 2
0%
1)
1*
1+
1.
1/
10
01
14
15
16
07
#110
0"
#111
1"
b10100 &
1#
b10011 ,
1$
b10011 2
1%
0)
0*
0+
1'
0/
00
05
06
#112
0"
#113
1"
b01001 &
b0111 ,
b0111 2
0'
0-
03
#114
0"
#115
1"
b10010 &
0#
b01110 ,
0$
b01110 2
0%
1)
1*
1+
0.
1/
10
04
15
16
#116
0"
#117
1"
b0100 &
1#
b11100 ,
b11100 2
0)
0*
0+
0/
00
11
05
06
17
#118
0"
#119
1"
b01000 &
0#
b11000 ,
1$
b11000 2
1%
#120
0"
#121
1"
b10000 &
b10000 ,
b10000 2
1'
01
1-
07
13
#122
0"
#123
1"
b01 &
1#
b01 ,
b01 2
0'
1.
1/
10
11
14
15
16
17
#124
0"
#125
1"
b010 &
0#
b011 ,
0$
b011 2
0%
1)
1*
1+
1'
0/
00
01
0-
05
06
07
03
#126
0"
#127
1"
b0101 &
b0110 ,
b0110 2
0)
0*
0+
0'
0.
1/
10
11
1-
04
15
16
17
13
#128
0"
#129
1"
b01010 &
b01101 ,
b01101 2
1)
1*
1+
1'
1.
01
0-
14
07
03
#130
0"
#131
1"
b10101 &
b11010 ,
b11010 2
0)
0*
0+
0.
1-
04
13
#132
0"
#133
1"
b01011 &
1#
b10101 ,
1$
b10101 2
1%
1)
1*
1+
1.
11
0-
14
17
03
#134
0"
#135
1"
b10111 &
0#
b01010 ,
b01010 2
0'
0.
01
04
07
#136
0"
#137
1"
b01110 &
1#
b10100 ,
0$
b10100 2
0%
1'
0/
00
1-
05
06
13
#138
0"
#139
1"
b11101 &
0#
b01001 ,
1$
b01001 2
1%
0)
0*
0+
1.
1/
10
0-
14
15
16
03
#140
0"
#141
1"
b11011 &
1#
b10010 ,
0$
b10010 2
0%
1)
1*
1+
0'
0.
11
04
17
#142
0"
#143
1"
b10110 &
b0100 ,
1$
b0100 2
1%
0/
00
01
05
06
07
#144
0"
#145
1"
b01100 &
b01000 ,
0$
b01000 2
0%
0)
0*
0+
11
1-
17
13
#146
0"
#147
1"
b11000 &
0#
b10001 ,
b10001 2
1'
1.
1/
10
0-
14
15
16
03
#148
0"
#149
1"
b10001 &
1#
b010 ,
1$
b010 2
1%
0.
1-
04
13
#150
0"
#151
1"
b011 &
b0101 ,
0$
b0101 2
0%
1)
1*
1+
1.
14
#152
0"
#153
1"
b0111 &
0#
b01011 ,
b01011 2
0/
00
05
06
#154
0"
#155
1"
b01111 &
b10111 ,
b10111 2
01
07
#156
0"
#157
1"
b11111 &
b01111 ,
1$
b01111 2
1%
0'
11
17
#158
0"
#159
1"
b11110 &
1#
b11111 ,
0$
b11111 2
0%
0-
03
#160
0"
#161
1"
b11100 &
b11110 ,
1$
b11110 2
1%
0)
0*
0+
1'
0.
1/
10
01
1-
04
15
16
07
13
#162
0"
#163
1"
b11001 &
b11101 ,
b11101 2
1.
14
#164
0"
#165
1"
b10011 &
b11011 ,
b11011 2
1)
1*
1+
0'
0/
00
11
0-
05
06
17
03
#166
0"
#167
1"
b0110 &
b10110 ,
b10110 2
1'
0.
1/
10
04
15
16
#168
0"
#169
1"
b01101 &
0#
b01100 ,
b01100 2
0)
0*
0+
0'
0/
00
1-
05
06
13
#170
0"
#171
1"
b11010 &
b11001 ,
0$
b11001 2
0%
1)
1*
1+
1.
1/
10
01
14
15
16
07
#172
0"
#173
1"
b10100 &
1#
b10011 ,
1$
b10011 2
1%
0)
0*
0+
1'
0/
00
05
06
#174
0"
#175
1"
b01001 &
b0111 ,
b0111 2
0'
0-
03
#176
0"
#177
1"
b10010 &
0#
b01110 ,
0$
b01110 2
0%
1)
1*
1+
0.
1/
10
04
15
16
#178
0"
#179
1"
b0100 &
1#
b11100 ,
b11100 2
0)
0*
0+
0/
00
11
05
06
17
#180
0"
#181
1"
b01000 &
0#
b11000 ,
1$
b11000 2
1%
#182
0"
#183
1"
b10000 &
b10000 ,
b10000 2
1'
01
1-
07
13
#184
0"
#185
1"
b01 &
1#
b01 ,
b01 2
0'
1.
1/
10
11
14
15
16
17
#186
0"
#187
1"
b010 &
0#
b011 ,
0$
b011 2
0%
1)
1*
1+
1'
0/
00
01
0-
05
06
07
03
#188
0"
#189
1"
b0101 &
b0110 ,
b0110 2
0)
0*
0+
0'
0.
1/
10
11
1-
04
15
16
17
13
#190
0"
#191
1"
b01010 &
b01101 ,
b01101 2
1)
1*
1+
1'
1.
01
0-
14
07
03
#192
0"
#193
1"
b10101 &
b11010 ,
b11010 2
0)
0*
0+
0.
1-
04
13
#194
0"
#195
1"
b01011 &
1#
b10101 ,
1$
b10101 2
1%
1)
1*
1+
1.
11
0-
14
17
03
#196
0"
#197
1"
b10111 &
0#
b01010 ,
b01010 2
0'
0.
01
04
07
#198
0"
#199
1"
b01110 &
1#
b10100 ,
0$
b10100 2
0%
1'
0/
00
1-
05
06
13
#200
0"
#201
1"
b11101 &
0#
b01001 ,
1$
b01001 2
1%
0)
0*
0+
1.
1/
10
0-
14
15
16
03
#202
0"
#203
1"
b11011 &
1#
b10010 ,
0$
b10010 2
0%
1)
1*
1+
0'
0.
11
04
17
#204
0"
#205
1"
b10110 &
b0100 ,
1$
b0100 2
1%
0/
00
01
05
06
07
#206
0"
#207
1"
b01100 &
b01000 ,
0$
b01000 2
0%
0)
0*
0+
11
1-
17
13
#208
0"
#209
1"
b11000 &
0#
b10001 ,
b10001 2
1'
1.
1/
10
0-
14
15
16
03
#210
0"
#211
1"
b10001 &
1#
b010 ,
1$
b010 2
1%
0.
1-
04
13
#212
0"
#213
1"
b011 &
b0101 ,
0$
b0101 2
0%
1)
1*
1+
1.
14
#214
0"
#215
1"
b0111 &
0#
b01011 ,
b01011 2
0/
00
05
06
#216
0"
#217
1"
b01111 &
b10111 ,
b10111 2
01
07
#218
0"
#219
1"
b11111 &
b01111 ,
1$
b01111 2
1%
0'
11
17
#220
0"
#221
1"
b11110 &
1#
b11111 ,
0$
b11111 2
0%
0-
03
#222
0"
#223
1"
b11100 &
b11110 ,
1$
b11110 2
1%
0)
0*
0+
1'
0.
1/
10
01
1-
04
15
16
07
13
#224
0"
#225
1"
b11001 &
b11101 ,
b11101 2
1.
14
#226
0"
#227
1"
b10011 &
b11011 ,
b11011 2
1)
1*
1+
0'
0/
00
11
0-
05
06
17
03
#228
0"
#229
1"
b0110 &
b10110 ,
b10110 2
1'
0.
1/
10
04
15
16
#230
0"
#231
1"
b01101 &
0#
b01100 ,
b01100 2
0)
0*
0+
0'
0/
00
1-
05
06
13
#232
0"
#233
1"
b11010 &
b11001 ,
0$
b11001 2
0%
1)
1*
1+
1.
1/
10
01
14
15
16
07
#234
0"
#235
1"
b10100 &
1#
b10011 ,
1$
b10011 2
1%
0)
0*
0+
1'
0/
00
05
06
#236
0"
#237
1"
b01001 &
b0111 ,
b0111 2
0'
0-
03
#238
0"
#239
1"
b10010 &
0#
b01110 ,
0$
b01110 2
0%
1)
1*
1+
0.
1/
10
04
15
16
#240
0"
#241
1"
b0100 &
1#
b11100 ,
b11100 2
0)
0*
0+
0/
00
11
05
06
17
#242
0"
#243
1"
b01000 &
0#
b11000 ,
1$
b11000 2
1%
#244
0"
#245
1"
b10000 &
b10000 ,
b10000 2
1'
01
1-
07
13
#246
0"
#247
1"
b01 &
1#
b01 ,
b01 2
0'
1.
1/
10
11
14
15
16
17
#248
0"
#249
1"
b010 &
0#
b011 ,
0$
b011 2
0%
1)
1*
1+
1'
0/
00
01
0-
05
06
07
03
#250
0"
#251
1"
b0101 &
b0110 ,
b0110 2
0)
0*
0+
0'
0.
1/
10
11
1-
04
15
16
17
13
#252
0"
#253
1"
b01010 &
b01101 ,
b01101 2
1)
1*
1+
1'
1.
01
0-
14
07
03
#254
0"
#255
1"
b10101 &
b11010 ,
b11010 2
0)
0*
0+
0.
1-
04
13
#256
0"
#257
1"
b01011 &
1#
b10101 ,
1$
b10101 2
1%
1)
1*
1+
1.
11
0-
14
17
03
#258
0"
#259
1"
b10111 &
0#
b01010 ,
b01010 2
0'
0.
01
04
07
#260
0"
#261
1"
b01110 &
1#
b10100 ,
0$
b10100 2
0%
1'
0/
00
1-
05
06
13
#262
0"
#263
1"
b11101 &
0#
b01001 ,
1$
b01001 2
1%
0)
0*
0+
1.
1/
10
0-
14
15
16
03
#264
0"
#265
1"
b11011 &
1#
b10010 ,
0$
b10010 2
0%
1)
1*
1+
0'
0.
11
04
17
#266
0"
#267
1"
b10110 &
b0100 ,
1$
b0100 2
1%
0/
00
01
05
06
07
#268
0"
#269
1"
b01100 &
b01000 ,
0$
b01000 2
0%
0)
0*
0+
11
1-
17
13
#270
0"
#271
1"
b11000 &
0#
b10001 ,
b10001 2
1'
1.
1/
10
0-
14
15
16
03
#272
0"
#273
1"
b10001 &
1#
b010 ,
1$
b010 2
1%
0.
1-
04
13
#274
0"
#275
1"
b011 &
b0101 ,
0$
b0101 2
0%
1)
1*
1+
1.
14
#276
0"
#277
1"
b0111 &
0#
b01011 ,
b01011 2
0/
00
05
06
#278
0"
#279
1"
b01111 &
b10111 ,
b10111 2
01
07
#280
0"
#281
1"
b11111 &
b01111 ,
1$
b01111 2
1%
0'
11
17
#282
0"
#283
1"
b11110 &
1#
b11111 ,
0$
b11111 2
0%
0-
03
#284
0"
#285
1"
b11100 &
b11110 ,
1$
b11110 2
1%
0)
0*
0+
1'
0.
1/
10
01
1-
04
15
16
07
13
#286
0"
#287
1"
b11001 &
b11101 ,
b11101 2
1.
14
#288
0"
#289
1"
b10011 &
b11011 ,
b11011 2
1)
1*
1+
0'
0/
00
11
0-
05
06
17
03
#290
0"
#291
1"
b0110 &
b10110 ,
b10110 2
1'
0.
1/
10
04
15
16
#292
0"
#293
1"
b01101 &
0#
b01100 ,
b01100 2
0)
0*
0+
0'
0/
00
1-
05
06
13
#294
0"
#295
1"
b11010 &
b11001 ,
0$
b11001 2
0%
1)
1*
1+
1.
1/
10
01
14
15
16
07
#296
0"
#297
1"
b10100 &
1#
b10011 ,
1$
b10011 2
1%
0)
0*
0+
1'
0/
00
05
06
#298
0"
#299
1"
b01001 &
b0111 ,
b0111 2
0'
0-
03
#300
0"
#301
1"
b10010 &
0#
b01110 ,
0$
b01110 2
0%
1)
1*
1+
0.
1/
10
04
15
16
#302
0"
#303
1"
b0100 &
1#
b11100 ,
b11100 2
0)
0*
0+
0/
00
11
05
06
17
#304
0"
#305
1"
b01000 &
0#
b11000 ,
1$
b11000 2
1%
#306
0"
#307
1"
b10000 &
b10000 ,
b10000 2
1'
01
1-
07
13
#308
0"
#309
1"
b01 &
1#
b01 ,
b01 2
0'
1.
1/
10
11
14
15
16
17
#310
0"
#311
1"
b010 &
0#
b011 ,
0$
b011 2
0%
1)
1*
1+
1'
0/
00
01
0-
05
06
07
03
#312
0"
#313
1"
b0101 &
b0110 ,
b0110 2
0)
0*
0+
0'
0.
1/
10
11
1-
04
15
16
17
13
#314
0"
#315
1"
b01010 &
b01101 ,
b01101 2
1)
1*
1+
1'
1.
01
0-
14
07
03
#316
0"
#317
1"
b10101 &
b11010 ,
b11010 2
0)
0*
0+
0.
1-
04
13
#318
0"
#319
1"
b01011 &
1#
b10101 ,
1$
b10101 2
1%
1)
1*
1+
1.
11
0-
14
17
03
#320
0"
#321
1"
b10111 &
0#
b01010 ,
b01010 2
0'
0.
01
04
07
#322
0"
#323
1"
b01110 &
1#
b10100 ,
0$
b10100 2
0%
1'
0/
00
1-
05
06
13
#324
0"
#325
1"
b11101 &
0#
b01001 ,
1$
b01001 2
1%
0)
0*
0+
1.
1/
10
0-
14
15
16
03
#326
0"
#327
1"
b11011 &
1#
b10010 ,
0$
b10010 2
0%
1)
1*
1+
0'
0.
11
04
17
#328
0"
#329
1"
b10110 &
b0100 ,
1$
b0100 2
1%
0/
00
01
05
06
07
#330
0"
#331
1"
b01100 &
b01000 ,
0$
b01000 2
0%
0)
0*
0+
11
1-
17
13
#332
0"
#333
1"
b11000 &
0#
b10001 ,
b10001 2
1'
1.
1/
10
0-
14
15
16
03
#334
0"
#335
1"
b10001 &
1#
b010 ,
1$
b010 2
1%
0.
1-
04
13
#336
0"
#337
1"
b011 &
b0101 ,
0$
b0101 2
0%
1)
1*
1+
1.
14
#338
0"
#339
1"
b0111 &
0#
b01011 ,
b01011 2
0/
00
05
06
#340
0"
#341
1"
b01111 &
b10111 ,
b10111 2
01
07
#342
0"
#343
1"
b11111 &
b01111 ,
1$
b01111 2
1%
0'
11
17
#344
0"
#345
1"
b11110 &
1#
b11111 ,
0$
b11111 2
0%
0-
03
#346
0"
#347
1"
b11100 &
b11110 ,
1$
b11110 2
1%
0)
0*
0+
1'
0.
1/
10
01
1-
04
15
16
07
13
#348
0"
#349
1"
b11001 &
b11101 ,
b11101 2
1.
14
#350
0"
#351
1"
b10011 &
b11011 ,
b11011 2
1)
1*
1+
0'
0/
00
11
0-
05
06
17
03
#352
0"
#353
1"
b0110 &
b10110 ,
b10110 2
1'
0.
1/
10
04
15
16
#354
0"
#355
1"
b01101 &
0#
b01100 ,
b01100 2
0)
0*
0+
0'
0/
00
1-
05
06
13
#356
0"
#357
1"
b11010 &
b11001 ,
0$
b11001 2
0%
1)
1*
1+
1.
1/
10
01
14
15
16
07
#358
0"
#359
1"
b10100 &
1#
b10011 ,
1$
b10011 2
1%
0)
0*
0+
1'
0/
00
05
06
#360
0"
#361
1"
b01001 &
b0111 ,
b0111 2
0'
0-
03
#362
0"
#363
1"
b10010 &
0#
b01110 ,
0$
b01110 2
0%
1)
1*
1+
0.
1/
10
04
15
16
#364
0"
#365
1"
b0100 &
1#
b11100 ,
b11100 2
0)
0*
0+
0/
00
11
05
06
17
#366
0"
#367
1"
b01000 &
0#
b11000 ,
1$
b11000 2
1%
#368
0"
#369
1"
b10000 &
b10000 ,
b10000 2
1'
01
1-
07
13
#370
0"
#371
1"
b01 &
1#
b01 ,
b01 2
0'
1.
1/
10
11
14
15
16
17
#372
0"
#373
1"
b010 &
0#
b011 ,
0$
b011 2
0%
1)
1*
1+
1'
0/
00
01
0-
05
06
07
03
#374
0"
#375
1"
b0101 &
b0110 ,
b0110 2
0)
0*
0+
0'
0.
1/
10
11
1-
04
15
16
17
13
#376
0"
#377
1"
b01010 &
b01101 ,
b01101 2
1)
1*
1+
1'
1.
01
0-
14
07
03
#378
0"
#379
1"
b10101 &
b11010 ,
b11010 2
0)
0*
0+
0.
1-
04
13
#380
0"
#381
1"
b01011 &
1#
b10101 ,
1$
b10101 2
1%
1)
1*
1+
1.
11
0-
14
17
03
#382
0"
#383
1"
b10111 &
0#
b01010 ,
b01010 2
0'
0.
01
04
07
#384
0"
#385
1"
b01110 &
1#
b10100 ,
0$
b10100 2
0%
1'
0/
00
1-
05
06
13
#386
0"
#387
1"
b11101 &
0#
b01001 ,
1$
b01001 2
1%
0)
0*
0+
1.
1/
10
0-
14
15
16
03
#388
0"
#389
1"
b11011 &
1#
b10010 ,
0$
b10010 2
0%
1)
1*
1+
0'
0.
11
04
17
#390
0"
#391
1"
b10110 &
b0100 ,
1$
b0100 2
1%
0/
00
01
05
06
07
#392
0"
#393
1"
b01100 &
b01000 ,
0$
b01000 2
0%
0)
0*
0+
11
1-
17
13
#394
0"
#395
1"
b11000 &
0#
b10001 ,
b10001 2
1'
1.
1/
10
0-
14
15
16
03
#396
0"
#397
1"
b10001 &
1#
b010 ,
1$
b010 2
1%
0.
1-
04
13
#398
0"
#399
1"
b011 &
b0101 ,
0$
b0101 2
0%
1)
1*
1+
1.
14
#400
0"
#401
1"
b0111 &
0#
b01011 ,
b01011 2
0/
00
05
06
#402
0"
#403
1"
b01111 &
b10111 ,
b10111 2
01
07
#404
0"
#405
1"
b11111 &
b01111 ,
1$
b01111 2
1%
0'
11
17
#406
0"
#407
1"
b11110 &
1#
b11111 ,
0$
b11111 2
0%
0-
03
#408
0"
#409
1"
b11100 &
b11110 ,
1$
b11110 2
1%
0)
0*
0+
1'
0.
1/
10
01
1-
04
15
16
07
13
#410
0"
#411
1"
b11001 &
b11101 ,
b11101 2
1.
14
#412
0"
#413
1"
b10011 &
b11011 ,
b11011 2
1)
1*
1+
0'
0/
00
11
0-
05
06
17
03
#414
0"
#415
1"
b0110 &
b10110 ,
b10110 2
1'
0.
1/
10
04
15
16
#416
0"
#417
1"
b01101 &
0#
b01100 ,
b01100 2
0)
0*
0+
0'
0/
00
1-
05
06
13
#418
0"
#419
1"
b11010 &
b11001 ,
0$
b11001 2
0%
1)
1*
1+
1.
1/
10
01
14
15
16
07
#420
0"
#421
1"
b10100 &
1#
b10011 ,
1$
b10011 2
1%
0)
0*
0+
1'
0/
00
05
06
#422
0"
#423
1"
b01001 &
b0111 ,
b0111 2
0'
0-
03
#424
0"
#425
1"
b10010 &
0#
b01110 ,
0$
b01110 2
0%
1)
1*
1+
0.
1/
10
04
15
16
#426
0"
#427
1"
b0100 &
1#
b11100 ,
b11100 2
0)
0*
0+
0/
00
11
05
06
17
#428
0"
#429
1"
b01000 &
0#
b11000 ,
1$
b11000 2
1%
#430
0"
#431
1"
b10000 &
b10000 ,
b10000 2
1'
01
1-
07
13
#432
0"
#433
1"
b01 &
1#
b01 ,
b01 2
0'
1.
1/
10
11
14
15
16
17
#434
0"
