ex8_2/arbiter/design/controller.sv
// < The Controller >
//
// The type of arbiter we will be making is a basic queue based controller where up to 3 modules can request access to the shared resource and we will allow for multiple commands 
// to be performed before releasing.
//
// To get started let's create a new file called controller.v with the following empty module:
`default_nettype none

module memController
(
  // The first 3 ports are the actual ports required to create the arbiter, the rest of the connections are to actually control the bus to the shared memory. 
  input wire clk, 

  // So for example the first module will get bit 0 the second bit 1 and the third bit 2. 'requestingMemory' can hold values like the following:
  input wire [2:0] requestingMemory, // bit - one for each module that wants to use the shared resource. It can can hold values like the following: 3'b011
  output reg [2:0] grantedAccess = 0, // bit - which will store the bit of the module who is currently in control. It will only have a single bit active at a time. Values like: 3'b010
 
  // The next 4 ports comprise the output bus to the shared resource - we connect those outputs the "shared resorce". Note we don't include 'dataFromMem' here as all modules can share 
  // those lines since there is only a single driver (the shared memory) as opposed to 'dataToMem' where we have 3 drivers (the 3 modules requesting access) so they need to be muxed.
  output reg enabled,
  output reg [7:0] address, 
  output reg [31:0] dataToMem, 
  output reg readWrite,  

  // The rest of the ports are just the different options we can connect to the output - these inputs are commenected to the "separate modules":
  input wire [7:0] addr1, //  is the address from module #1
  input wire [7:0] addr2, //  is the address from module #2
  input wire [7:0] addr3, //  is the address from module #3
  
  // The same for 'dataToMem' data bus, and ... 
  input wire [31:0] dataToMem1,
  input wire [31:0] dataToMem2,
  input wire [31:0] dataToMem3, 
  // ... the 'readWrite' flag.
  input wire readWrite1,
  input wire readWrite2,
  input wire readWrite3
  // Basically based on who is granted access we will connect the corresponding modules inputs to the outputs going to the shared  memory.
);

// So our module has two roles: 
//  - one is to decide who is granted access
//  - the other role is to connect the wires based on who has access acting as the bus controller.
//
// Just as a side note, these two roles can be separated, so you can have a more general purpose arbiter which only has the first 3 ports here, so it only outputs who is currently 
// 'grantedAccess' based on the requests, and then have a separate module which takes that info and controls the connection to the shared memory.

// Next let's create some registers inside:
reg [2:0] queue [0:3] = '{default:'0}; // 3-bits wide - [2:0] - to store a module number 'grantedAccess' (so each bit represents a different module), 4 counts [0:3] - natural roll over
reg [2:0] currentlyInQueue = 0; // will store whether or not one of the modules is already in the queue. This is in the format of 'requestingMemory' where each bit is a different
                                // module and they can all be 1 at the same time.
//  implement a circular fifo queue we need to indices, one for each end of our queue.
reg [1:0] queueNextIndex = 0; // for indexing of 4 - represents the next index where we should place a value, this is the end of our queue,
reg [1:0] queueCurrIndex = 0; // for indexing of 4 - which is the first value in the queue (the one we will be giving access to) so they represent the two edges of the queue.

// When we insert a new value into the queue we increment 'queueNextIndex' and when we use a value from the beginning of the queue we increment 'queueCurrIndex'. If the two indices are 
// equal it means the queue is empty, and because we chose a power of 2 as the queue size we don't need to handle wrapping around to the beginning in our circular queue, it will happen
// automatically.
//
// Next let's add two "helper" wires which we can use to simplify the modules task:
wire [2:0] requestsNotInQueue; // 'requestsNotInQueue' is basically the opposite of 'currentlyInQueue' but with the trait - they are requesting access (they want to be in the queue)
wire [2:0] nextInLine; // 'nextInLine' will store one out of the possible 3 modules requesting access as we can only handle 1 request at a time.

// We can already assign these two wires as follows: 
assign requestsNotInQueue = (requestingMemory & ~currentlyInQueue); // get a list of modules not in the queue, but that want to be in the queue.
assign nextInLine = requestsNotInQueue[0] ? 3'b001 : requestsNotInQueue[1] ? 3'b010 : 3'b100; // is simply the first bit that is currently requesting and not in the queue. 
assign enabled = grantedAccess[0] | grantedAccess[1] | grantedAccess[2]; // is high if control to the shared resource is currently granted to one of the 3 modules,
// 'nextInLine' is simply the first bit that is currently requesting and not in the queue. Again this is because in our module we can only add a single request to our queue per clock 
// cycle, so at each iteration we need only a single requester, this is what is stored in 'nextInLine'.
//
// Finally 'enabled' is high if control to the shared resource is currently granted to one of the 3 modules, we OR all the bits together, this is the same as checking whether it doesn't
// equal zero.

// Now let's handle adding someone to the queue:
always_ff @(posedge clk) begin  // On each clock cycle we see ...
  // First, check if we need to add a request to the queue ... 
  if(requestsNotInQueue != 0) begin  // ... if there are modules requesting access that are still not in the queue using our helper wire we just hooked up...
    queue[queueNextIndex] <= nextInLine; // If so, we place 'nextInLine' which is one of the three modules (e.g. 3'b010 for module 2) and we place it in the queue at the next available index.
    currentlyInQueue <= currentlyInQueue | nextInLine; // Set the module's corresponding bit in 'currentlyInQueue' to 1 so that it won't be added again to the queue ...
    queueNextIndex <= queueNextIndex + 1; //  and finally we increment 'queueNextIndex' to point at the next available index where a request should be added.
  // Otherwise, check whether to remove a request from the queue when someone releases control.
  end else if(enabled && (requestingMemory & grantedAccess) == 0) begin  // Check, if access is currently being granted to someone, and, if the person currently granted access is no longer requesting access.
                                                                         // By 'ANDing' the bit of the current module controlling the shared memory with the requests we isolate that specific bit, and then if it 
                                                                         // equals zero we know they released control.
    queueCurrIndex <= queueCurrIndex + 1; // // So if we are currently granting access to someone and they have stopped requesting access, we will remove them from the queue by incrementing 'queueCurrIndex'.
    currentlyInQueue <= currentlyInQueue & (~grantedAccess); // unset the bit from 'currentlyInQueue' corresponding to this module.
    grantedAccess <= 3'b000;  // clear 'grantedAccess' to zero, thus removing the access for this module
  end
  // The final section in our always block is to actually give access to the module at the start of our queue.
  if(~enabled && queueNextIndex != queueCurrIndex) begin  // if no any access given and the two indices for next available and current queue item are not equal (which would signify an empty queue)... 
    grantedAccess <= queue[queueCurrIndex]; // ... then we can give the next in line access. This can happen in parallel to adding / removing module requests from the queue.
  end 
  //
end 
// The reason this is in an 'else if', instead of happening in parallel, is because they both are setting values for 'currentlyInQueue' which will cause verilog to take the last update if 
// both were to happen losing data of a module being added to the queue. So we can either add a new module request to the queue or remove a request from the queue, not both at the same
// time.

// With that the only thing left to do here is to actually mux the wires to the shared memory based on who is currently 'grantedAccess'. So at the bottom of our module (outside the 
// always block) add the following:
assign address  = (grantedAccess[0]) ? addr1 :     // output from module #1
                  (grantedAccess[1]) ? addr2 :     // output from module #2
                  (grantedAccess[2]) ? addr3 : 0;  // output from module #3

assign readWrite = (grantedAccess[0]) ? readWrite1 :    // output from module #1
                   (grantedAccess[1]) ? readWrite2 :    // output from module #2
                   (grantedAccess[2]) ? readWrite3 : 0; // output from module #3

assign dataToMem = (grantedAccess[0]) ? dataToMem1 :    // output from module #1 
                   (grantedAccess[1]) ? dataToMem2 :    // output from module #2
                   (grantedAccess[2]) ? dataToMem3 : 0; // output from module #3
// For each of the ports we need to mux, we simply check which bit is currently high and based on that connect output to the corresponding modules input.
endmodule

// We should now have a working arbiter which will allow for up to 3 modules to share our memory module we created. Now before building an example let's create a testbench so that we
// can visually verify that the controller is working.

ex8_2/arbiter/testbench/controller_tb.sv
// < Testing Our Controller >
// To test our module and create a VCD file where we can visualize our module in action we can create a file called controller_tb.v with the following:

`timescale 10ns/1ns
module test();
  reg clk = 0;

  // Clock generator - simple toggle each #1 clk cycle
  always begin  
    #1 clk = ~clk; // The #number (#1) is a special simulation syntax from iverilog that allows us to delay something by a certain number of time frames. 
                   // By saying each time interval the clock alternates, we are saying the clock cycle is 2 time units (1 high cycle and 1 low cycle is 1 clock cycle).
                   // So this loop will wait 1 time unit and toggle the clock register.
  end 

  // Configuration section - for setting Start & Stop of test bench duration
  initial begin 
    $display("Starting CONTROLLER Test") ; // print out a string optionally injecting variables into it - performed once
    #1000 $finish; // stops the simulation, so after 1000 more time frames we stop the simulation.
  end
 
  // Configuration section - for visually debugging the logic we can add another block to dump a VCD file.
  initial begin 
    $dumpfile("controller.vcd");  // $dumpfile chooses the name of the file - VCD file 
    $dumpvars(0,test);  // chooses what to save and how many levels of nested objects to save. By sending 0 as the number of layers it means we want all nested layers
                        // (which will include our Controller Test module), and by sending the top module test it means store everything and all child wires / registers.
  end
 
  // This creates a blank module with a clock that flips once per frame and we setup the simulation to end after 1000 frames. The last block will output anything defined in 
  // this module into a VCD file.
  //
  // So next we only need to instantiate our controller and we will be able to test it:
  reg req1 = 1, req2 = 1, req3 = 1; // init state - all 3 modules requesting access, at the same time
  wire [2:0] grantedAccess;
  wire enabled;

  wire [7:0] address;
  wire [31:0] dataToMem;
  wire readWrite;

  reg [7:0] addr1 = 8'hA1;   
  reg [7:0] addr2 = 8'hA2;
  reg [7:0] addr3 = 8'hA3;

  reg [31:0] dataToMem1 = 32'hD1;
  reg [31:0] dataToMem2 = 32'hD2;
  reg [31:0] dataToMem3 = 32'hD3;


  memController fc(
    clk,                  // .clk
    {req3, req2, req1},   // .requestingMemory
    grantedAccess,        
    enabled,              // connected to the "resource"  
    address,              // connected to the "resource" 
    dataToMem,            // connected to the "resource" 
    readWrite,            // connected to the "resource" 
    addr1,
    addr2,
    addr3,
    dataToMem1,           
    dataToMem2,
    dataToMem3,
    1'b0,                 // .readWrite1 (coming from module #1) - wants to write
    1'b1,                 // .readWrite2 (coming from module #2) - wants to read 
    1'b0                  // .readWrite3 (coming from module #3) - wants to write
  );

// We go through creating all the registers and wires required to instantiate our controller. We won't really have modules using the shared memory, so in terms of address we will 
// use a static address to simulate this, same for the data we will just hardcode a value.
//
// Next to really test the requeing we need a way to simulate a module releasing access once granted and then to re-request access making it get re-added to the queue. We can do this
// by just adding a counter for example we will count 4 frames and then release the shared resource:
reg [1:0] counter = 0;
always_ff @(posedge clk) begin 
  if(enabled) begin 
    counter <= counter + 1;
    if(counter == 2'b11) begin 
      if(grantedAccess == 3'b001) begin 
        req1 <= 0;
      end else if (grantedAccess == 3'b010) begin 
        req2 <= 0;
      end else if (grantedAccess == 3'b100) begin 
        req3 <= 0;
      end
    end
  end else begin 
    counter <= 0;
    req1 <= 1; 
    req2 <= 1; 
    req3 <= 1;
  end
end 

// So when the 'enabled' wire is high, we count up four frames and then set the corresponding request bit to zero. Otherwise in-between when modules are currently granted access we reset
// all request bits to 1.
//
// We could have shortened this by having the request bits be a single register and using the same method as we used in the controller for setting unsetting 'currentlyInQueue', but I think 
// this allows for better visualization when viewing the VCD file as we can see each bit separated on its own line.
endmodule

// You can compile and run this with the following commands:
// iverilog -o controller_test.o -s test controller.v controller_tb.v
// vvp controller_test.o
// You should then see a VCD file called controller.vcd. Looking through this file we can see that everything seems to be working great:

// < Observing the generated testbench waveform: >
//
// On the first line we can see that each module receives the resource for 4 frames and we can see the order repeating and that each module is getting it's time on the resource. On the last 
// line we can see the address coming out from the controller and we see it match the hardcoded address for each of our 3 input modules.
//
// In the middle you can see how it adds each requesting module to the queue 1 at a time and how the indices wrap around giving us an endless circular queue.
//
// With everything working as expected we can now move on to actually running it on the tang nano.

ex8_2/arbiter/simulation/controller_waves.vcd
$date 
$end
$version DSim 2025.0.1
$end
$timescale 1 ns $end
$scope module $pkgs $end
$scope module std $end
$scope function randomize $end
$upscope $end
$upscope $end
$upscope $end
$scope module $unit $end
$upscope $end
$scope module test $end
$scope module fc $end
$var wire 8 + addr1[7:0] $end
$var wire 8 , addr2[7:0] $end
$var wire 8 - addr3[7:0] $end
$var reg 8 ( address[7:0] $end
$var wire 1 " clk $end
$var reg 3 7 currentlyInQueue[2:0] $end
$var reg 32 ) dataToMem[31:0] $end
$var wire 32 . dataToMem1[31:0] $end
$var wire 32 / dataToMem2[31:0] $end
$var wire 32 0 dataToMem3[31:0] $end
$var reg 1 ' enabled $end
$var reg 3 2 grantedAccess[2:0] $end
$var wire 3 ; nextInLine[2:0] $end
$var reg 2 9 queueCurrIndex[1:0] $end
$var reg 2 8 queueNextIndex[1:0] $end
$var reg 1 * readWrite $end
$var wire 1 3 readWrite1 $end
$var wire 1 4 readWrite2 $end
$var wire 1 5 readWrite3 $end
$var wire 3 1 requestingMemory[2:0] $end
$var wire 3 : requestsNotInQueue[2:0] $end
$upscope $end
$var reg 8 + addr1[7:0] $end
$var reg 8 , addr2[7:0] $end
$var reg 8 - addr3[7:0] $end
$var wire 8 ( address[7:0] $end
$var reg 1 " clk $end
$var reg 2 < counter[1:0] $end
$var wire 32 ) dataToMem[31:0] $end
$var reg 32 . dataToMem1[31:0] $end
$var reg 32 / dataToMem2[31:0] $end
$var reg 32 0 dataToMem3[31:0] $end
$var wire 1 ' enabled $end
$var wire 3 & grantedAccess[2:0] $end
$var wire 1 * readWrite $end
$var reg 1 # req1 $end
$var reg 1 $ req2 $end
$var reg 1 % req3 $end
$upscope $end
$enddefinitions $end
#0
$dumpvars
b10100001 +
b10100010 ,
b10100011 -
bx (
0"
b0 7
bx )
b011010001 .
b011010010 /
b011010011 0
x'
b0 2
bx ;
b0 9
b0 8
x*
x3
x4
x5
bx 1
bx :
b10100001 +
b10100010 ,
b10100011 -
bx (
0"
b0 <
bx )
b011010001 .
b011010010 /
b011010011 0
x'
bx &
x*
1#
1$
1%
$end
bx1 1
bx11 1
b111 1
b0 &
03
14
05
b111 :
b01 ;
0'
0*
b0 (
b0 )
#10
1"
b01 7
b01 8
b110 :
b010 ;
#20
0"
#30
1"
b011 7
b10 8
b01 2
b10100001 (
b011010001 )
b01 &
b100 :
1'
b100 ;
#40
0"
#50
1"
b01 <
b111 7
b11 8
b0 :
#60
0"
#70
1"
b10 <
#80
0"
#90
1"
b11 <
#100
0"
#110
1"
b0 <
0#
b110 1
#120
0"
#130
1"
b01 <
b01 9
b110 7
b0 2
b0 (
b0 )
b0 &
0'
#140
0"
#150
1"
b0 <
1#
b010 2
b111 1
b10100010 (
b011010010 )
b010 &
1'
1*
b01 :
b01 ;
#160
0"
#170
1"
b01 <
b111 7
b0 8
b0 :
b100 ;
#180
0"
#190
1"
b10 <
#200
0"
#210
1"
b11 <
#220
0"
#230
1"
b0 <
0$
b101 1
#240
0"
#250
1"
b01 <
b10 9
b101 7
b0 2
b0 (
b0 )
b0 &
0'
0*
#260
0"
#270
1"
b0 <
1$
b100 2
b111 1
b10100011 (
b011010011 )
b100 &
1'
b010 :
b010 ;
#280
0"
#290
1"
b01 <
b111 7
b01 8
b0 :
b100 ;
#300
0"
#310
1"
b10 <
#320
0"
#330
1"
b11 <
#340
0"
#350
1"
b0 <
0%
b011 1
#360
0"
#370
1"
b01 <
b11 9
b011 7
b0 2
b0 (
b0 )
b0 &
0'
#380
0"
#390
1"
b0 <
1%
b01 2
b111 1
b10100001 (
b011010001 )
b01 &
1'
b100 :
#400
0"
#410
1"
b01 <
b111 7
b10 8
b0 :
#420
0"
#430
1"
b10 <
#440
0"
#450
1"
b11 <
#460
0"
#470
1"
b0 <
0#
b110 1
#480
0"
#490
1"
b01 <
b0 9
b110 7
b0 2
b0 (
b0 )
b0 &
0'
#500
0"
#510
1"
b0 <
1#
b010 2
b111 1
b10100010 (
b011010010 )
b010 &
1'
1*
b01 :
b01 ;
#520
0"
#530
1"
b01 <
b111 7
b11 8
b0 :
b100 ;
#540
0"
#550
1"
b10 <
#560
0"
#570
1"
b11 <
#580
0"
#590
1"
b0 <
0$
b101 1
#600
0"
#610
1"
b01 <
b01 9
b101 7
b0 2
b0 (
b0 )
b0 &
0'
0*
#620
0"
#630
1"
b0 <
1$
b100 2
b111 1
b10100011 (
b011010011 )
b100 &
1'
b010 :
b010 ;
#640
0"
#650
1"
b01 <
b111 7
b0 8
b0 :
b100 ;
#660
0"
#670
1"
b10 <
#680
0"
#690
1"
b11 <
#700
0"
#710
1"
b0 <
0%
b011 1
#720
0"
#730
1"
b01 <
b10 9
b011 7
b0 2
b0 (
b0 )
b0 &
0'
#740
0"
#750
1"
b0 <
1%
b01 2
b111 1
b10100001 (
b011010001 )
b01 &
1'
b100 :
#760
0"
#770
1"
b01 <
b111 7
b01 8
b0 :
#780
0"
#790
1"
b10 <
#800
0"
#810
1"
b11 <
#820
0"
#830
1"
b0 <
0#
b110 1
#840
0"
#850
1"
b01 <
b11 9
b110 7
b0 2
b0 (
b0 )
b0 &
0'
#860
0"
#870
1"
b0 <
1#
b010 2
b111 1
b10100010 (
b011010010 )
b010 &
1'
1*
b01 :
b01 ;
#880
0"
#890
1"
b01 <
b111 7
b10 8
b0 :
b100 ;
#900
0"
#910
1"
b10 <
#920
0"
#930
1"
b11 <
#940
0"
#950
1"
b0 <
0$
b101 1
#960
0"
#970
1"
b01 <
b0 9
b101 7
b0 2
b0 (
b0 )
b0 &
0'
0*
#980
0"
#990
1"
b0 <
1$
b100 2
b111 1
b10100011 (
b011010011 )
b100 &
1'
b010 :
b010 ;
#1000
0"
#1010
1"
b01 <
b111 7
b11 8
b0 :
b100 ;
#1020
0"
#1030
1"
b10 <
#1040
0"
#1050
1"
b11 <
#1060
0"
#1070
1"
b0 <
0%
b011 1
#1080
0"
#1090
1"
b01 <
b01 9
b011 7
b0 2
b0 (
b0 )
b0 &
0'
#1100
0"
#1110
1"
b0 <
1%
b01 2
b111 1
b10100001 (
b011010001 )
b01 &
1'
b100 :
#1120
0"
#1130
1"
b01 <
b111 7
b0 8
b0 :
#1140
0"
#1150
1"
b10 <
#1160
0"
#1170
1"
b11 <
#1180
0"
#1190
1"
b0 <
0#
b110 1
#1200
0"
#1210
1"
b01 <
b10 9
b110 7
b0 2
b0 (
b0 )
b0 &
0'
#1220
0"
#1230
1"
b0 <
1#
b010 2
b111 1
b10100010 (
b011010010 )
b010 &
1'
1*
b01 :
b01 ;
#1240
0"
#1250
1"
b01 <
b111 7
b01 8
b0 :
b100 ;
#1260
0"
#1270
1"
b10 <
#1280
0"
#1290
1"
b11 <
#1300
0"
#1310
1"
b0 <
0$
b101 1
#1320
0"
#1330
1"
b01 <
b11 9
b101 7
b0 2
b0 (
b0 )
b0 &
0'
0*
#1340
0"
#1350
1"
b0 <
1$
b100 2
b111 1
b10100011 (
b011010011 )
b100 &
1'
b010 :
b010 ;
#1360
0"
#1370
1"
b01 <
b111 7
b10 8
b0 :
b100 ;
#1380
0"
#1390
1"
b10 <
#1400
0"
#1410
1"
b11 <
#1420
0"
#1430
1"
b0 <
0%
b011 1
#1440
0"
#1450
1"
b01 <
b0 9
b011 7
b0 2
b0 (
b0 )
b0 &
0'
#1460
0"
#1470
1"
b0 <
1%
b01 2
b111 1
b10100001 (
b011010001 )
b01 &
1'
b100 :
#1480
0"
#1490
1"
b01 <
b111 7
b11 8
b0 :
#1500
0"
#1510
1"
b10 <
#1520
0"
#1530
1"
b11 <
#1540
0"
#1550
1"
b0 <
0#
b110 1
#1560
0"
#1570
1"
b01 <
b01 9
b110 7
b0 2
b0 (
b0 )
b0 &
0'
#1580
0"
#1590
1"
b0 <
1#
b010 2
b111 1
b10100010 (
b011010010 )
b010 &
1'
1*
b01 :
b01 ;
#1600
0"
#1610
1"
b01 <
b111 7
b0 8
b0 :
b100 ;
#1620
0"
#1630
1"
b10 <
#1640
0"
#1650
1"
b11 <
#1660
0"
#1670
1"
b0 <
0$
b101 1
#1680
0"
#1690
1"
b01 <
b10 9
b101 7
b0 2
b0 (
b0 )
b0 &
0'
0*
#1700
0"
#1710
1"
b0 <
1$
b100 2
b111 1
b10100011 (
b011010011 )
b100 &
1'
b010 :
b010 ;
#1720
0"
#1730
1"
b01 <
b111 7
b01 8
b0 :
b100 ;
#1740
0"
#1750
1"
b10 <
#1760
0"
#1770
1"
b11 <
#1780
0"
#1790
1"
b0 <
0%
b011 1
#1800
0"
#1810
1"
b01 <
b11 9
b011 7
b0 2
b0 (
b0 )
b0 &
0'
#1820
0"
#1830
1"
b0 <
1%
b01 2
b111 1
b10100001 (
b011010001 )
b01 &
1'
b100 :
#1840
0"
#1850
1"
b01 <
b111 7
b10 8
b0 :
#1860
0"
#1870
1"
b10 <
#1880
0"
#1890
1"
b11 <
#1900
0"
#1910
1"
b0 <
0#
b110 1
#1920
0"
#1930
1"
b01 <
b0 9
b110 7
b0 2
b0 (
b0 )
b0 &
0'
#1940
0"
#1950
1"
b0 <
1#
b010 2
b111 1
b10100010 (
b011010010 )
b010 &
1'
1*
b01 :
b01 ;
#1960
0"
#1970
1"
b01 <
b111 7
b11 8
b0 :
b100 ;
#1980
0"
#1990
1"
b10 <
#2000
0"
#2010
1"
b11 <
#2020
0"
#2030
1"
b0 <
0$
b101 1
#2040
0"
#2050
1"
b01 <
b01 9
b101 7
b0 2
b0 (
b0 )
b0 &
0'
0*
#2060
0"
#2070
1"
b0 <
1$
b100 2
b111 1
b10100011 (
b011010011 )
b100 &
1'
b010 :
b010 ;
#2080
0"
#2090
1"
b01 <
b111 7
b0 8
b0 :
b100 ;
#2100
0"
#2110
1"
b10 <
#2120
0"
#2130
1"
b11 <
#2140
0"
#2150
1"
b0 <
0%
b011 1
#2160
0"
#2170
1"
b01 <
b10 9
b011 7
b0 2
b0 (
b0 )
b0 &
0'
#2180
0"
#2190
1"
b0 <
1%
b01 2
b111 1
b10100001 (
b011010001 )
b01 &
1'
b100 :
#2200
0"
#2210
1"
b01 <
b111 7
b01 8
b0 :
#2220
0"
#2230
1"
b10 <
#2240
0"
#2250
1"
b11 <
#2260
0"
#2270
1"
b0 <
0#
b110 1
#2280
0"
#2290
1"
b01 <
b11 9
b110 7
b0 2
b0 (
b0 )
b0 &
0'
#2300
0"
#2310
1"
b0 <
1#
b010 2
b111 1
b10100010 (
b011010010 )
b010 &
1'
1*
b01 :
b01 ;
#2320
0"
#2330
1"
b01 <
b111 7
b10 8
b0 :
b100 ;
#2340
0"
#2350
1"
b10 <
#2360
0"
#2370
1"
b11 <
#2380
0"
#2390
1"
b0 <
0$
b101 1
#2400
0"
#2410
1"
b01 <
b0 9
b101 7
b0 2
b0 (
b0 )
b0 &
0'
0*
#2420
0"
#2430
1"
b0 <
1$
b100 2
b111 1
b10100011 (
b011010011 )
b100 &
1'
b010 :
b010 ;
#2440
0"
#2450
1"
b01 <
b111 7
b11 8
b0 :
b100 ;
#2460
0"
#2470
1"
b10 <
#2480
0"
#2490
1"
b11 <
#2500
0"
#2510
1"
b0 <
0%
b011 1
#2520
0"
#2530
1"
b01 <
b01 9
b011 7
b0 2
b0 (
b0 )
b0 &
0'
#2540
0"
#2550
1"
b0 <
1%
b01 2
b111 1
b10100001 (
b011010001 )
b01 &
1'
b100 :
#2560
0"
#2570
1"
b01 <
b111 7
b0 8
b0 :
#2580
0"
#2590
1"
b10 <
#2600
0"
#2610
1"
b11 <
#2620
0"
#2630
1"
b0 <
0#
b110 1
#2640
0"
#2650
1"
b01 <
b10 9
b110 7
b0 2
b0 (
b0 )
b0 &
0'
#2660
0"
#2670
1"
b0 <
1#
b010 2
b111 1
b10100010 (
b011010010 )
b010 &
1'
1*
b01 :
b01 ;
#2680
0"
#2690
1"
b01 <
b111 7
b01 8
b0 :
b100 ;
#2700
0"
#2710
1"
b10 <
#2720
0"
#2730
1"
b11 <
#2740
0"
#2750
1"
b0 <
0$
b101 1
#2760
0"
#2770
1"
b01 <
b11 9
b101 7
b0 2
b0 (
b0 )
b0 &
0'
0*
#2780
0"
#2790
1"
b0 <
1$
b100 2
b111 1
b10100011 (
b011010011 )
b100 &
1'
b010 :
b010 ;
#2800
0"
#2810
1"
b01 <
b111 7
b10 8
b0 :
b100 ;
#2820
0"
#2830
1"
b10 <
#2840
0"
#2850
1"
b11 <
#2860
0"
#2870
1"
b0 <
0%
b011 1
#2880
0"
#2890
1"
b01 <
b0 9
b011 7
b0 2
b0 (
b0 )
b0 &
0'
#2900
0"
#2910
1"
b0 <
1%
b01 2
b111 1
b10100001 (
b011010001 )
b01 &
1'
b100 :
#2920
0"
#2930
1"
b01 <
b111 7
b11 8
b0 :
#2940
0"
#2950
1"
b10 <
#2960
0"
#2970
1"
b11 <
#2980
0"
#2990
1"
b0 <
0#
b110 1
#3000
0"
#3010
1"
b01 <
b01 9
b110 7
b0 2
b0 (
b0 )
b0 &
0'
#3020
0"
#3030
1"
b0 <
1#
b010 2
b111 1
b10100010 (
b011010010 )
b010 &
1'
1*
b01 :
b01 ;
#3040
0"
#3050
1"
b01 <
b111 7
b0 8
b0 :
b100 ;
#3060
0"
#3070
1"
b10 <
#3080
0"
#3090
1"
b11 <
#3100
0"
#3110
1"
b0 <
0$
b101 1
#3120
0"
#3130
1"
b01 <
b10 9
b101 7
b0 2
b0 (
b0 )
b0 &
0'
0*
#3140
0"
#3150
1"
b0 <
1$
b100 2
b111 1
b10100011 (
b011010011 )
b100 &
1'
b010 :
b010 ;
#3160
0"
#3170
1"
b01 <
b111 7
b01 8
b0 :
b100 ;
#3180
0"
#3190
1"
b10 <
#3200
0"
#3210
1"
b11 <
#3220
0"
#3230
1"
b0 <
0%
b011 1
#3240
0"
#3250
1"
b01 <
b11 9
b011 7
b0 2
b0 (
b0 )
b0 &
0'
#3260
0"
#3270
1"
b0 <
1%
b01 2
b111 1
b10100001 (
b011010001 )
b01 &
1'
b100 :
#3280
0"
#3290
1"
b01 <
b111 7
b10 8
b0 :
#3300
0"
#3310
1"
b10 <
#3320
0"
#3330
1"
b11 <
#3340
0"
#3350
1"
b0 <
0#
b110 1
#3360
0"
#3370
1"
b01 <
b0 9
b110 7
b0 2
b0 (
b0 )
b0 &
0'
#3380
0"
#3390
1"
b0 <
1#
b010 2
b111 1
b10100010 (
b011010010 )
b010 &
1'
1*
b01 :
b01 ;
#3400
0"
#3410
1"
b01 <
b111 7
b11 8
b0 :
b100 ;
#3420
0"
#3430
1"
b10 <
#3440
0"
#3450
1"
b11 <
#3460
0"
#3470
1"
b0 <
0$
b101 1
#3480
0"
#3490
1"
b01 <
b01 9
b101 7
b0 2
b0 (
b0 )
b0 &
0'
0*
#3500
0"
#3510
1"
b0 <
1$
b100 2
b111 1
b10100011 (
b011010011 )
b100 &
1'
b010 :
b010 ;
#3520
0"
#3530
1"
b01 <
b111 7
b0 8
b0 :
b100 ;
#3540
0"
#3550
1"
b10 <
#3560
0"
#3570
1"
b11 <
#3580
0"
#3590
1"
b0 <
0%
b011 1
#3600
0"
#3610
1"
b01 <
b10 9
b011 7
b0 2
b0 (
b0 )
b0 &
0'
#3620
0"
#3630
1"
b0 <
1%
b01 2
b111 1
b10100001 (
b011010001 )
b01 &
1'
b100 :
#3640
0"
#3650
1"
b01 <
b111 7
b01 8
b0 :
#3660
0"
#3670
1"
b10 <
#3680
0"
#3690
1"
b11 <
#3700
0"
#3710
1"
b0 <
0#
b110 1
#3720
0"
#3730
1"
b01 <
b11 9
b110 7
b0 2
b0 (
b0 )
b0 &
0'
#3740
0"
#3750
1"
b0 <
1#
b010 2
b111 1
b10100010 (
b011010010 )
b010 &
1'
1*
b01 :
b01 ;
#3760
0"
#3770
1"
b01 <
b111 7
b10 8
b0 :
b100 ;
#3780
0"
#3790
1"
b10 <
#3800
0"
#3810
1"
b11 <
#3820
0"
#3830
1"
b0 <
0$
b101 1
#3840
0"
#3850
1"
b01 <
b0 9
b101 7
b0 2
b0 (
b0 )
b0 &
0'
0*
#3860
0"
#3870
1"
b0 <
1$
b100 2
b111 1
b10100011 (
b011010011 )
b100 &
1'
b010 :
b010 ;
#3880
0"
#3890
1"
b01 <
b111 7
b11 8
b0 :
b100 ;
#3900
0"
#3910
1"
b10 <
#3920
0"
#3930
1"
b11 <
#3940
0"
#3950
1"
b0 <
0%
b011 1
#3960
0"
#3970
1"
b01 <
b01 9
b011 7
b0 2
b0 (
b0 )
b0 &
0'
#3980
0"
#3990
1"
b0 <
1%
b01 2
b111 1
b10100001 (
b011010001 )
b01 &
1'
b100 :
#4000
0"
#4010
1"
b01 <
b111 7
b0 8
b0 :
#4020
0"
#4030
1"
b10 <
#4040
0"
#4050
1"
b11 <
#4060
0"
#4070
1"
b0 <
0#
b110 1
#4080
0"
#4090
1"
b01 <
b10 9
b110 7
b0 2
b0 (
b0 )
b0 &
0'
#4100
0"
#4110
1"
b0 <
1#
b010 2
b111 1
b10100010 (
b011010010 )
b010 &
1'
1*
b01 :
b01 ;
#4120
0"
#4130
1"
b01 <
b111 7
b01 8
b0 :
b100 ;
#4140
0"
#4150
1"
b10 <
#4160
0"
#4170
1"
b11 <
#4180
0"
#4190
1"
b0 <
0$
b101 1
#4200
0"
#4210
1"
b01 <
b11 9
b101 7
b0 2
b0 (
b0 )
b0 &
0'
0*
#4220
0"
#4230
1"
b0 <
1$
b100 2
b111 1
b10100011 (
b011010011 )
b100 &
1'
b010 :
b010 ;
#4240
0"
#4250
1"
b01 <
b111 7
b10 8
b0 :
b100 ;
#4260
0"
#4270
1"
b10 <
#4280
0"
#4290
1"
b11 <
#4300
0"
#4310
1"
b0 <
0%
b011 1
#4320
0"
#4330
1"
b01 <
b0 9
b011 7
b0 2
b0 (
b0 )
b0 &
0'
#4340
0"
#4350
1"
b0 <
1%
b01 2
b111 1
b10100001 (
b011010001 )
b01 &
1'
b100 :
#4360
0"
#4370
1"
b01 <
b111 7
b11 8
b0 :
#4380
0"
#4390
1"
b10 <
#4400
0"
#4410
1"
b11 <
#4420
0"
#4430
1"
b0 <
0#
b110 1
#4440
0"
#4450
1"
b01 <
b01 9
b110 7
b0 2
b0 (
b0 )
b0 &
0'
#4460
0"
#4470
1"
b0 <
1#
b010 2
b111 1
b10100010 (
b011010010 )
b010 &
1'
1*
b01 :
b01 ;
#4480
0"
#4490
1"
b01 <
b111 7
b0 8
b0 :
b100 ;
#4500
0"
#4510
1"
b10 <
#4520
0"
#4530
1"
b11 <
#4540
0"
#4550
1"
b0 <
0$
b101 1
#4560
0"
#4570
1"
b01 <
b10 9
b101 7
b0 2
b0 (
b0 )
b0 &
0'
0*
#4580
0"
#4590
1"
b0 <
1$
b100 2
b111 1
b10100011 (
b011010011 )
b100 &
1'
b010 :
b010 ;
#4600
0"
#4610
1"
b01 <
b111 7
b01 8
b0 :
b100 ;
#4620
0"
#4630
1"
b10 <
#4640
0"
#4650
1"
b11 <
#4660
0"
#4670
1"
b0 <
0%
b011 1
#4680
0"
#4690
1"
b01 <
b11 9
b011 7
b0 2
b0 (
b0 )
b0 &
0'
#4700
0"
#4710
1"
b0 <
1%
b01 2
b111 1
b10100001 (
b011010001 )
b01 &
1'
b100 :
#4720
0"
